odoo/addons/product_template_tags_code/README.rst
odoo/addons/product_template_tags_code/__init__.py
odoo/addons/product_template_tags_code/__manifest__.py
odoo/addons/product_template_tags_code/i18n/ca.po
odoo/addons/product_template_tags_code/i18n/es.po
odoo/addons/product_template_tags_code/i18n/it.po
odoo/addons/product_template_tags_code/i18n/product_template_tags_code.pot
odoo/addons/product_template_tags_code/migrations/13.0.1.0.0/post-migration.py
odoo/addons/product_template_tags_code/models/__init__.py
odoo/addons/product_template_tags_code/models/product_template_tag.py
odoo/addons/product_template_tags_code/readme/CONFIGURE.rst
odoo/addons/product_template_tags_code/readme/CONTRIBUTORS.rst
odoo/addons/product_template_tags_code/readme/DESCRIPTION.rst
odoo/addons/product_template_tags_code/static/description/icon.png
odoo/addons/product_template_tags_code/static/description/index.html
odoo/addons/product_template_tags_code/tests/__init__.py
odoo/addons/product_template_tags_code/tests/test_product_template_tags.py
odoo/addons/product_template_tags_code/views/product_template_tag.xml
odoo13_addon_product_template_tags_code-13.0.1.0.1.dev10.dist-info/METADATA
odoo13_addon_product_template_tags_code-13.0.1.0.1.dev10.dist-info/WHEEL
odoo13_addon_product_template_tags_code-13.0.1.0.1.dev10.dist-info/top_level.txt
odoo13_addon_product_template_tags_code-13.0.1.0.1.dev10.dist-info/RECORD
