Metadata-Version: 2.1
Name: odoo13-addon-product-template-tags-code
Version: 13.0.1.0.1.dev10
Summary: This addon allow to add code on products tags
Home-page: https://github.com/OCA/product-attribute
Author: Camptocamp SA, Odoo Community Association (OCA)
Author-email: support@odoo-community.org
License: AGPL-3
Platform: UNKNOWN
Classifier: Programming Language :: Python
Classifier: Framework :: Odoo
Classifier: Framework :: Odoo :: 13.0
Classifier: License :: OSI Approved :: GNU Affero General Public License v3
Requires-Python: >=3.5
Requires-Dist: odoo13-addon-product-template-tags
Requires-Dist: odoo <13.1dev,>=13.0a
